emspy/__init__.py
emspy/common.py
emspy/connection.py
emspy/query/__init__.py
emspy/query/aircraft.py
emspy/query/airport.py
emspy/query/analytic.py
emspy/query/analyticset.py
emspy/query/asset.py
emspy/query/dbmodify.py
emspy/query/ems.py
emspy/query/fleet.py
emspy/query/flight.py
emspy/query/flightphase.py
emspy/query/fltquery.py
emspy/query/localdata.py
emspy/query/profile.py
emspy/query/query.py
emspy/query/tsquery.py
emspy-0.6.6.dist-info/LICENSE
emspy-0.6.6.dist-info/METADATA
emspy-0.6.6.dist-info/WHEEL
emspy-0.6.6.dist-info/top_level.txt
emspy-0.6.6.dist-info/RECORD
