Metadata-Version: 2.1
Name: emspy
Version: 0.6.6
Summary: A Python EMS RESTful API Client/Wrapper
Home-page: https://github.com/ge-flight-analytics/emspy
Author: GE Flight Analytics
Author-email: AviationAdiSupport@ge.com
License: MIT
Classifier: Programming Language :: Python :: 2.7
Classifier: Programming Language :: Python :: 3
Classifier: License :: OSI Approved :: MIT License
License-File: LICENSE
Requires-Dist: numpy >=1.13.3
Requires-Dist: pandas
Requires-Dist: future
Requires-Dist: networkx
